<?xml version="1.0" encoding="UTF-8" standalone="yes"?>
<CompanyHierarchy xmlns:xsi="http://www.w3.org/2001/XMLSchema-instance" xmlns:xsd="http://www.w3.org/2001/XMLSchema" state="OK">
 <RootCompany fullname="Открытое акционерное общество &quot;Новороссийский морской торговый порт&quot;" id="01125867" name="ОАО &quot;Новороссийский морской торговый порт&quot;" />
 <ChildCompanies>
  <ChildCompany fullname="Открытое Акционерное Общество &quot;ИПП&quot;" id="d100334066" name="ОАО &quot;ИПП&quot;" parentId="01125867" primaryId="59272" topChild="false" percentShare="99.98" amountShare="2 059 900,00" />
  <ChildCompany fullname="Закрытое акционерное общество &quot;Геленджикский морской порт&quot;" id="d110136120" name="ЗАО &quot;Геленджикский морской порт&quot;" parentId="01125867" primaryId="66627" topChild="false" percentShare="2.00" amountShare="40 000,00" />
  <ChildCompany fullname="Общество с ограниченной ответственностью &quot;Балтийская Стивидорная Компания&quot;" id="d113640333" name="ООО &quot;Балтийская Стивидорная Компания&quot;" parentId="01125867" primaryId="895904" topChild="false" percentShare="100.00" amountShare="10 000,00" />
  <ChildCompany fullname="Новороссийский Клуб Портовиков - Структурное Подразделение Открытого Акционерного Общества &quot;Новороссийский Морской Торговый Порт&quot;" id="d126394746" name="ФЛ &quot;Новороссийский Клуб Портовиков&quot; ОАО &quot;Нмтп&quot;" parentId="01125867" primaryId="78121" topChild="false" percentShare="-1" amountShare="" />
  <ChildCompany fullname="Открытое акционерное общество &quot;ОТП Банк&quot;" id="d129293885" name="ОАО &quot;ОТП Банк&quot;" parentId="01125867" primaryId="1903763" topChild="false" percentShare="5.12" amountShare="143 177 736,47" />
  <ChildCompany fullname="Открытое акционерное общество &quot;Флот Новороссийского морского торгового порта&quot;" id="d129597585" name="ОАО &quot;Флот Новороссийского морского торгового порта" parentId="01125867" primaryId="86271" topChild="false" percentShare="50.00" amountShare="80 400,00" />
  <ChildCompany fullname="Закрытое акционерное общество &quot;ЛУКОЙЛ-Черноморье&quot;" id="d133745063" name="ЗАО &quot;ЛУКОЙЛ-Черноморье&quot;" parentId="01125867" primaryId="95180" topChild="false" percentShare="24.00" amountShare="24 000,00" />
  <ChildCompany fullname="Морской Порт &quot;Анапа&quot; - Обособленное Подразделение Открытого Акционерного Общества &quot;Новороссийский Морской Торговый Порт&quot;" id="d134989548" name="Морской Порт &quot;Анапа&quot; ОАО &quot;Нмтп&quot;" parentId="01125867" primaryId="97178" topChild="false" percentShare="-1" amountShare="" />
  <ChildCompany fullname="Представительство Открытого акционерного общества &quot;Новороссийский морской торговый порт&quot; в городе Москве" id="d140150347" name="ПРЕД ОАО &quot;НМТП&quot; в г Москве" parentId="01125867" primaryId="1925450" topChild="false" percentShare="-1" amountShare="" />
  <ChildCompany fullname="Ассоциация &quot;Консорциум Предприятий Новороссийского Транспортного Узла&quot;" id="d145835280" name="&quot;Кпнту&quot;" parentId="01125867" primaryId="107475" topChild="false" percentShare="25.00" amountShare="0,00" />
  <ChildCompany fullname="Общество с ограниченной ответственностью &quot;Новороссийский мазутный терминал&quot;" id="d161946814" name="ООО &quot;Новороссийский мазутный терминал&quot;" parentId="01125867" primaryId="5349328" topChild="false" percentShare="50.00" amountShare="500 000 001,00" />
  <ChildCompany fullname="Общество с ограниченной ответственностью &quot;Приморский торговый порт&quot;" id="d170650573" name="ООО &quot;ПТП&quot;" parentId="01125867" primaryId="1742756" topChild="false" percentShare="100.00" amountShare="3 010 000,00" />
  <ChildCompany fullname="Автономная некоммерческая организация &quot;Учебный центр Новороссийского порта&quot;" id="d187949201" name="АНО &quot;Учебный центр Новороссийского порта&quot;" parentId="01125867" primaryId="5077673" topChild="false" percentShare="-1" amountShare="" />
  <ChildCompany fullname="Филиал &quot;Омский&quot; Открытого акционерного общества &quot;ОТП Банк&quot;" id="d2_09227886_29293885" name="Фл &quot;Омский&quot; ОАО &quot;ОТП Банк&quot;" parentId="d129293885" primaryId="3217281" topChild="false" percentShare="-1" amountShare="" />
  <ChildCompany fullname="Открытое Акционерное Общество &quot;Геленджик-Банк&quot;" id="d2_09801931_33745063" name="ОАО &quot;Геленджик-Банк&quot;" parentId="d133745063" primaryId="64609" topChild="false" percentShare="16.05" amountShare="2 044 770,00" />
  <ChildCompany fullname="Закрытое акционерное общество &quot;Морское агентство &quot;Новоторик&quot;" id="d2_10138293_33745063" name="ЗАО &quot;Морское агентство &quot;Новоторик&quot;" parentId="d133745063" primaryId="66688" topChild="false" percentShare="100.00" amountShare="450 000,00" />
  <ChildCompany fullname="Выборгский Филиал Закрытого Акционерного Общества &quot;Лукойл-черноморье&quot;" id="d2_11180643_33745063" name="ФЛ Выборгский ЗАО &quot;Лукойл-черноморье&quot;" parentId="d133745063" primaryId="1699243" topChild="false" percentShare="-1" amountShare="" />
  <ChildCompany fullname="Открытое акционерное общество &quot;Новороссийский зерновой терминал&quot;" id="d2_14010485_29597585" name="ОАО &quot;Новороссийский зерновой терминал&quot;" parentId="d129597585" primaryId="69004" topChild="false" percentShare="-1" amountShare="950,00" />
  <ChildCompany fullname="Мурманский филиал ЗАО &quot;ЛУКОЙЛ-Черноморье&quot;" id="d2_14764089_33745063" name="ФЛ ЗАО &quot;ЛУКОЙЛ-Черноморье&quot; г Мурманск" parentId="d133745063" primaryId="3020710" topChild="false" percentShare="-1" amountShare="" />
  <ChildCompany fullname="Новороссийский Городской Фонд &quot;НАШ Город&quot;" id="d2_15372256_33745063" name="Фонд &quot;НАШ Город&quot;" parentId="d133745063" primaryId="70956" topChild="false" percentShare="-1" amountShare="" />
  <ChildCompany fullname="Некоммерческое партнерство &quot;Об'единение по Защите Интересов Акционеров Предприятий и Организаций&quot;" id="d2_18707131_29293885" name="Некоммерческое Партнерство &quot;Опиак&quot;" parentId="d129293885" primaryId="1879764" topChild="false" percentShare="-1" amountShare="" />
  <ChildCompany fullname="Архангельский Филиал ЗАО &quot;Лукойл-черноморье&quot;" id="d2_22195091_33745063" name="Архангельский ФЛ ЗАО &quot;Лукойл-черноморье&quot;" parentId="d133745063" primaryId="445301" topChild="false" percentShare="-1" amountShare="" />
  <ChildCompany fullname="Операционный офис &quot;Волгоградский-2&quot; филиала &quot;Ростовский&quot; Открытого акционерного общества &quot;ОТП Банк&quot;" id="d2_22378839_29293885" name="Операционный офис &quot;Волгоградский-2&quot; филиала &quot;Росто" parentId="d129293885" primaryId="7685786" topChild="false" percentShare="-1" amountShare="" />
  <ChildCompany fullname="Филиал &quot;Дальневосточный&quot; Открытого акционерного общества &quot;ОТП Банк&quot;" id="d2_30938270_29293885" name="ОТП Банк филиал &quot;Дальневосточный&quot;" parentId="d129293885" primaryId="6469757" topChild="false" percentShare="-1" amountShare="" />
  <ChildCompany fullname="Негосударственный Пенсионный Фонд &quot;Первый Сберегательный Пенсионный Фонд&quot;" id="d2_40186931_29293885" name="НПФ &quot;Первый Сберегательный Пенсионный Фонд&quot;" parentId="d129293885" primaryId="1926381" topChild="false" percentShare="50.00" amountShare="100 000,00" />
  <ChildCompany fullname="Общество с ограниченной ответственностью &quot; Гамаюн&quot;" id="d2_43966026_29293885" name="ООО &quot;Гамаюн&quot;" parentId="d129293885" primaryId="3243211" topChild="false" percentShare="100.00" amountShare="6 325,00" />
  <ChildCompany fullname="Некоммерческая Организация &quot;Международный Инвестиционный Союз&quot;" id="d2_44509727_29293885" name="&quot;МИС&quot;" parentId="d129293885" primaryId="1993399" topChild="false" percentShare="12.50" amountShare="1,00" />
  <ChildCompany fullname="Закрытое акционерное общество &quot;Импортпищепром-Транссервис&quot;" id="d2_48436764_00334066" name="ЗАО &quot;Импортпищепром-Транссервис&quot;" parentId="d100334066" primaryId="111395" topChild="false" percentShare="12.63" amountShare="1 008,00" />
  <ChildCompany fullname="Кредитно-кассовый офис Открытое акционерное общество &quot;ОТП Банк&quot; в Санкт-Петербурге" id="d2_52181138_29293885" name="Кредитно-кассовый офис ОАО &quot;ОТП Банк&quot;" parentId="d129293885" primaryId="7405927" topChild="false" percentShare="-1" amountShare="" />
  <ChildCompany fullname="Представительство Акционерного Коммерческого Банка &quot;Банк Инвестиций и Сбережений&quot; (Закрытого Акционерного Общества) в Городе Санкт-петербурге" id="d2_53270053_29293885" name="Представительство АКБ &quot;Инвестсбербанк&quot;" parentId="d129293885" primaryId="1441378" topChild="false" percentShare="-1" amountShare="" />
  <ChildCompany fullname="Филиал &quot;Санкт-Петербургский&quot; Открытого акционерного общества &quot;ОТП Банк&quot;" id="d2_54314545_29293885" name="ФЛ &quot;Санкт-Петербургский&quot; ОАО &quot;ОТП Банк&quot;" parentId="d129293885" primaryId="1455874" topChild="false" percentShare="-1" amountShare="" />
  <ChildCompany fullname="Общество с Ограниченной Ответственностью &quot;Информ - Сервис&quot;" id="d2_54507675_29293885" name="ООО &quot;Информ - Сервис&quot;" parentId="d129293885" primaryId="3834642" topChild="false" percentShare="100.00" amountShare="8 400,00" />
  <ChildCompany fullname="Туапсинский Филиал Закрытого Акционерного Общества &quot;Лукойл-черноморье&quot;" id="d2_55119159_33745063" name="ФЛ ЗАО &quot;Лукойл-черноморье&quot;" parentId="d133745063" primaryId="125433" topChild="false" percentShare="-1" amountShare="" />
  <ChildCompany fullname="Астраханский филиал закрытого акционерного общества &quot;Лукойл-Черноморье&quot;" id="d2_56915266_33745063" name="ФЛ Астраханский ЗАО &quot;Лукойл-Черноморье&quot;" parentId="d133745063" primaryId="493203" topChild="false" percentShare="-1" amountShare="" />
  <ChildCompany fullname="Закрытое акционерное общество &quot;СоюзФлот Порт&quot;" id="d2_58569265_70650573" name="ЗАО &quot;СФП&quot;" parentId="d170650573" primaryId="1739629" topChild="false" percentShare="99.99" amountShare="1 049 900,00" />
  <ChildCompany fullname="Санкт-Петербургский филиал ЗАО &quot;ЛУКОЙЛ-Черноморье&quot;" id="d2_58886853_33745063" name="ФЛ ЗАО &quot;ЛУКОЙЛ-Черноморье&quot;" parentId="d133745063" primaryId="1495998" topChild="false" percentShare="-1" amountShare="" />
  <ChildCompany fullname="Некоммерческое Партнерство &quot;Ммсд&quot;" id="d2_59097288_29293885" name="НП &quot;Ммсд&quot;" parentId="d129293885" primaryId="2192013" topChild="false" percentShare="-1" amountShare="" />
  <ChildCompany fullname="Филиал &quot;Челябинский&quot; Открытого акционерного общества &quot;ОТП Банк&quot;" id="d2_61272391_29293885" name="&quot;ОТП Банк&quot; филиал &quot;Челябинский&quot;" parentId="d129293885" primaryId="5400499" topChild="false" percentShare="-1" amountShare="" />
  <ChildCompany fullname="Общество с ограниченной ответственностью &quot;Порт Петровск&quot;" id="d2_61969608_70650573" name="ООО &quot;Порт Петровск&quot;" parentId="d170650573" primaryId="5426409" topChild="false" percentShare="99.00" amountShare="99 000,00" />
  <ChildCompany fullname="Общество с ограниченной ответственностью &quot;Югтранснефть&quot;" id="d2_61969666_70650573" name="ООО &quot;Югтранснефть&quot;" parentId="d170650573" primaryId="5426414" topChild="false" percentShare="99.00" amountShare="99 000,00" />
  <ChildCompany fullname="Ростовский филиал Открытого акционерного общества &quot;ОТП Банк&quot;" id="d2_62288945_29293885" name="Фл &quot;Ростовский&quot; ОАО &quot;ОТП Банк&quot;" parentId="d129293885" primaryId="5682864" topChild="false" percentShare="-1" amountShare="" />
  <ChildCompany fullname="Кредитно-кассовый офис в г. Лиски филиала &quot;Ростовский&quot; ОАО &quot;ОТП Банк&quot;" id="d2_65649674_29293885" name="Кредитно-кассовый офис в г. Лиски ф-ла&quot;Ростовский&quot;" parentId="d129293885" primaryId="5738315" topChild="false" percentShare="-1" amountShare="" />
  <ChildCompany fullname="Калининградский филиал Закрытого акционерного общества &quot;ЛУКОЙЛ-Черноморье&quot;" id="d2_68792308_33745063" name="фл Калининградский ЗАО &quot;ЛУКОЙЛ-Черноморье&quot;" parentId="d133745063" primaryId="5957321" topChild="false" percentShare="-1" amountShare="" />
  <ChildCompany fullname="Рабочие места в г. Светлый Калининградской области-обособленное подразделение Закрытого акционерного общества &quot;Лукойл-Черноморье&quot;" id="d2_68807197_33745063" name="отд Рабочие места в г. Светлый Калининградской обл" parentId="d133745063" primaryId="6084764" topChild="false" percentShare="-1" amountShare="" />
  <ChildCompany fullname="Волгоградский Филиал Закрытого Акционерного Общества &quot;Лукойл-черноморье&quot;" id="d2_70598358_33745063" name="ФЛ &quot;Лукойл-черноморье&quot;" parentId="d133745063" primaryId="629525" topChild="false" percentShare="-1" amountShare="" />
  <ChildCompany fullname="Высоцкий Филиал Закрытого Акционерного Общества &quot;Лукойл-черноморье&quot;" id="d2_70639844_33745063" name="ФЛ Высоцкий ЗАО &quot;Лукойл-черноморье&quot;" parentId="d133745063" primaryId="1741877" topChild="false" percentShare="-1" amountShare="" />
  <ChildCompany fullname="Открытое акционерное общество &quot;Ростовская региональная ипотечная корпорация&quot;" id="d2_70678241_29293885" name="ОАО &quot;Ррик&quot;" parentId="d129293885" primaryId="3476980" topChild="false" percentShare="0.33" amountShare="500,00" />
  <ChildCompany fullname="Пермский филиал Закрытого акционерного общества &quot;ЛУКОЙЛ-Черноморье&quot;" id="d2_70861028_33745063" name="ФЛ ЗАО &quot;ЛУКОЙЛ-Черноморье&quot;" parentId="d133745063" primaryId="3377057" topChild="false" percentShare="-1" amountShare="" />
  <ChildCompany fullname="Ухтинский Филиал ЗАО &quot;Лукойл-черноморье&quot;" id="d2_71090892_33745063" name="ФЛ Ухтинский ЗАО &quot;Лукойл-черноморье&quot;" parentId="d133745063" primaryId="4411899" topChild="false" percentShare="-1" amountShare="" />
  <ChildCompany fullname="Брянский филиал ЗАО &quot;Лукойл-Черноморье&quot;" id="d2_71144731_33745063" name="Брянский фл ЗАО &quot;Лукойл-Черноморье&quot;" parentId="d133745063" primaryId="499506" topChild="false" percentShare="-1" amountShare="" />
  <ChildCompany fullname="Кстовский Филиал Закрытого Акционерного Общества &quot;Лукойл-черноморье&quot;" id="d2_71165012_33745063" name="Кствоский ФЛ ЗАО &quot;Лукойл-черноморье&quot;" parentId="d133745063" primaryId="753665" topChild="false" percentShare="-1" amountShare="" />
  <ChildCompany fullname="&quot;Центрально-Западный региональный центр&quot; - Представительство Открытого акционерного общества &quot;ОТП Банк&quot;" id="d2_71713442_29293885" name="Пред &quot;Центр.-Западный регион. центр&quot;ОАО&quot;ОТП Банк&quot;" parentId="d129293885" primaryId="966394" topChild="false" percentShare="-1" amountShare="" />
  <ChildCompany fullname="Представительство открытого акционерного общества &quot;ОТП Банк&quot;" id="d2_71786056_29293885" name="Пред ОАО &quot;ОТП Банк&quot;" parentId="d129293885" primaryId="853376" topChild="false" percentShare="-1" amountShare="" />
  <ChildCompany fullname="Байкальский Филиал Закрытого Акционерного Общества &quot;Лукойл-черноморье&quot;" id="d2_75084279_33745063" name="Байкальский ФЛ ЗАО &quot;Лукойл-черноморье&quot;" parentId="d133745063" primaryId="857343" topChild="false" percentShare="-1" amountShare="" />
  <ChildCompany fullname="Филиал &quot;Новосибирский&quot; Открытого Акционерного Общества &quot;ОТП Банк&quot;" id="d2_76680078_29293885" name="Филиал &quot;Новосибирский&quot; ОАО &quot;ОТП Банк&quot;" parentId="d129293885" primaryId="3140537" topChild="false" percentShare="-1" amountShare="" />
  <ChildCompany fullname="Обособленное Подразделение Закрытого Акционерного Общества &quot;Лукойл-черноморье&quot;" id="d2_79234267_33745063" name="Обособленное Подразделение ЗАО &quot;Лукойл-черноморье&quot;" parentId="d133745063" primaryId="3489862" topChild="false" percentShare="-1" amountShare="" />
  <ChildCompany fullname="Представительство &quot;Северо-Западный региональный центр&quot; Открытое акционерное общество &quot;ОТП Банк&quot;" id="d2_83772007_29293885" name="Представительство &quot;Северо-Западный региональный це" parentId="d129293885" primaryId="1617131" topChild="false" percentShare="-1" amountShare="" />
  <ChildCompany fullname="Филиал &quot;Самарский&quot; Открытого акционерного общества &quot;ОТП Банк&quot;" id="d2_88542393_29293885" name="ФЛ &quot;Самарский&quot; ОАО &quot;ОТП Банк&quot;" parentId="d129293885" primaryId="5117862" topChild="false" percentShare="-1" amountShare="" />
  <ChildCompany fullname="Операционный офис &quot;Нижегородский&quot; филиала &quot;Самарский&quot; Открытого акционерного общества &quot;ОТП Банк&quot;" id="d2_89384051_29293885" name="ОП &quot;Нижегородский&quot; ф-ла &quot;Самарский&quot; ОАО &quot;ОТП Банк&quot;" parentId="d129293885" primaryId="5164676" topChild="false" percentShare="-1" amountShare="" />
  <ChildCompany fullname="Федеральное агентство по управлению государственным имуществом" id="p100083629" name="Росимущество" parentId="01125867" primaryId="1769140" topChild="true" percentShare="20.00" amountShare="38 519 700,00" />
  <ChildCompany fullname="Граждане России" id="p1-8253969" name="Граждане России" parentId="01125867" primaryId="" topChild="true" percentShare="0.09" amountShare="173 000,00" />
  <ChildCompany fullname="юридические и физические лица" id="p1-8253971" name="юридические и физические лица" parentId="01125867" primaryId="" topChild="true" percentShare="50.11" amountShare="96 511 500,00" />
  <ChildCompany fullname="граждане Украины" id="p1-8253972" name="граждане Украины" parentId="01125867" primaryId="" topChild="true" percentShare="0.02" amountShare="43 600,00" />
  <ChildCompany fullname="прочие" id="p1-8253973" name="прочие" parentId="01125867" primaryId="" topChild="true" percentShare="11.18" amountShare="21 532 440,00" />
  <ChildCompany fullname="прочие" id="p1-8253974" name="прочие" parentId="01125867" primaryId="" topChild="true" percentShare="11.18" amountShare="21 532 440,00" />
  <ChildCompany fullname="прочие" id="p1-8253975" name="прочие" parentId="01125867" primaryId="" topChild="true" percentShare="11.18" amountShare="21 532 440,00" />
  <ChildCompany fullname="прочие" id="p1-8253976" name="прочие" parentId="01125867" primaryId="" topChild="true" percentShare="11.18" amountShare="21 532 440,00" />
  <ChildCompany fullname="прочие" id="p1-8253977" name="прочие" parentId="01125867" primaryId="" topChild="true" percentShare="11.18" amountShare="21 532 440,00" />
  <ChildCompany fullname="Правительство Российской Федерации" id="p200031093_p100083629" name="Правительство РФ" parentId="p100083629" primaryId="1767567" topChild="false" percentShare="-1" amountShare="" />
 </ChildCompanies>
</CompanyHierarchy>